{
  "acronym": "IPL",
  "name": "Indian Premier League",
  "edition": 2025,
  "gradient": "linear-gradient(135deg, darkblue, darkblue, orange)",
  "logo": "https://www.iplt20.com/assets/images/ipl-logo-new-old.png",
  "pointsTableColor": "darkblue",
  "teams": [
    {
      "acronym": "CSK",
      "name": "Chennai Super Kings",
      "logo": "https://documents.iplt20.com/ipl/CSK/logos/Logooutline/CSKoutline.png",
      "gradient": "linear-gradient(135deg, #FFC300, #FFC300, #003C71)"
    },
    {
      "acronym": "MI",
      "name": "Mumbai Indians",
      "logo": "https://documents.iplt20.com/ipl/MI/Logos/Logooutline/MIoutline.png",
      "gradient": "linear-gradient(135deg, #0033A0, #0033A0, #ffd700)"
    },
    {
      "acronym": "RCB",
      "name": "Royal Challengers Bengaluru",
      "logo": "https://documents.iplt20.com/ipl/RCB/Logos/Logooutline/RCBoutline.png",
      "gradient": "linear-gradient(135deg, #D50000, #D50000, black)"
    },
    {
      "acronym": "KKR",
      "name": "Kolkata Knight Riders",
      "logo": "https://documents.iplt20.com/ipl/KKR/Logos/Logooutline/KKRoutline.png",
      "gradient": "linear-gradient(135deg, #5A2D81, #5A2D81, gold)"
    },
    {
      "acronym": "DC",
      "name": "Delhi Capitals",
      "logo": "https://documents.iplt20.com/ipl/DC/Logos/LogoOutline/DCoutline.png",
      "gradient": "linear-gradient(135deg, #0033A0, #0033A0, #E4002B)"
    },
    {
      "acronym": "SRH",
      "name": "Sunrisers Hyderabad",
      "logo": "https://documents.iplt20.com/ipl/SRH/Logos/Logooutline/SRHoutline.png",
      "gradient": "linear-gradient(135deg, #D35400, #D35400, yellow)"
    },
    {
      "acronym": "RR",
      "name": "Rajasthan Royals",
      "logo": "https://documents.iplt20.com/ipl/RR/Logos/Logooutline/RRoutline.png",
      "gradient": "linear-gradient(135deg, #E91E63, #E91E63, deepskyblue)"
    },
    {
      "acronym": "PBKS",
      "name": "Punjab Kings",
      "logo": "https://documents.iplt20.com/ipl/PBKS/Logos/Logooutline/PBKSoutline.png",
      "gradient": "linear-gradient(135deg, red, red, gold)"
    },
    {
      "acronym": "LSG",
      "name": "Lucknow Super Giants",
      "logo": "https://documents.iplt20.com/ipl/LSG/Logos/Logooutline/LSGoutline.png",
      "gradient": "linear-gradient(135deg, #0CAFFF, #0CAFFF, #EF0107)"
    },
    {
      "acronym": "GT",
      "name": "Gujarat Titans",
      "logo": "https://documents.iplt20.com/ipl/GT/Logos/Logooutline/GToutline.png",
      "gradient": "linear-gradient(135deg, #041E42, #041E42, #FFCC00)"
    }
  ],
  "matches": [
    {
      "MatchNumber": 1,
      "DateUtc": "2025-03-22 14:00:00Z",
      "Location": "Eden Gardens",
      "HomeTeam": "KKR",
      "AwayTeam": "RCB",
      "result": "None",
      "status": "incomplete",
      "homeTeamRuns": 0,
      "homeTeamWickets": 0,
      "homeTeamOvers": 0,
      "awayTeamRuns": 0,
      "awayTeamWickets": 0,
      "awayTeamOvers": 0
    },
    {
      "MatchNumber": 2,
      "DateUtc": "2025-03-23 10:00:00Z",
      "Location": "Rajiv Gandhi International Stadium",
      "HomeTeam": "SRH",
      "AwayTeam": "RR",
      "result": "None",
      "status": "incomplete",
      "homeTeamRuns": 0,
      "homeTeamWickets": 0,
      "homeTeamOvers": 0,
      "awayTeamRuns": 0,
      "awayTeamWickets": 0,
      "awayTeamOvers": 0
    },
    {
      "MatchNumber": 3,
      "DateUtc": "2025-03-23 14:00:00Z",
      "Location": "MA Chidambaram Stadium",
      "HomeTeam": "CSK",
      "AwayTeam": "MI",
      "result": "None",
      "status": "incomplete",
      "homeTeamRuns": 0,
      "homeTeamWickets": 0,
      "homeTeamOvers": 0,
      "awayTeamRuns": 0,
      "awayTeamWickets": 0,
      "awayTeamOvers": 0
    },
    {
      "MatchNumber": 4,
      "DateUtc": "2025-03-24 14:00:00Z",
      "Location": "Dr YS Rajasekhara Reddy ACA-VDCA Cricket Stadium",
      "HomeTeam": "DC",
      "AwayTeam": "LSG",
      "result": "None",
      "status": "incomplete",
      "homeTeamRuns": 0,
      "homeTeamWickets": 0,
      "homeTeamOvers": 0,
      "awayTeamRuns": 0,
      "awayTeamWickets": 0,
      "awayTeamOvers": 0
    },
    {
      "MatchNumber": 5,
      "DateUtc": "2025-03-25 14:00:00Z",
      "Location": "Narendra Modi Stadium",
      "HomeTeam": "GT",
      "AwayTeam": "PBKS",
      "result": "None",
      "status": "incomplete",
      "homeTeamRuns": 0,
      "homeTeamWickets": 0,
      "homeTeamOvers": 0,
      "awayTeamRuns": 0,
      "awayTeamWickets": 0,
      "awayTeamOvers": 0
    },
    {
      "MatchNumber": 6,
      "DateUtc": "2025-03-26 14:00:00Z",
      "Location": "ACA Stadium",
      "HomeTeam": "RR",
      "AwayTeam": "KKR",
      "result": "None",
      "status": "incomplete",
      "homeTeamRuns": 0,
      "homeTeamWickets": 0,
      "homeTeamOvers": 0,
      "awayTeamRuns": 0,
      "awayTeamWickets": 0,
      "awayTeamOvers": 0
    },
    {
      "MatchNumber": 7,
      "DateUtc": "2025-03-27 14:00:00Z",
      "Location": "Rajiv Gandhi International Stadium",
      "HomeTeam": "SRH",
      "AwayTeam": "LSG",
      "result": "None",
      "status": "incomplete",
      "homeTeamRuns": 0,
      "homeTeamWickets": 0,
      "homeTeamOvers": 0,
      "awayTeamRuns": 0,
      "awayTeamWickets": 0,
      "awayTeamOvers": 0
    },
    {
      "MatchNumber": 8,
      "DateUtc": "2025-03-28 14:00:00Z",
      "Location": "MA Chidambaram Stadium",
      "HomeTeam": "CSK",
      "AwayTeam": "RCB",
      "result": "None",
      "status": "incomplete",
      "homeTeamRuns": 0,
      "homeTeamWickets": 0,
      "homeTeamOvers": 0,
      "awayTeamRuns": 0,
      "awayTeamWickets": 0,
      "awayTeamOvers": 0
    },
    {
      "MatchNumber": 9,
      "DateUtc": "2025-03-29 14:00:00Z",
      "Location": "Narendra Modi Stadium",
      "HomeTeam": "GT",
      "AwayTeam": "MI",
      "result": "None",
      "status": "incomplete",
      "homeTeamRuns": 0,
      "homeTeamWickets": 0,
      "homeTeamOvers": 0,
      "awayTeamRuns": 0,
      "awayTeamWickets": 0,
      "awayTeamOvers": 0
    },
    {
      "MatchNumber": 10,
      "DateUtc": "2025-03-30 10:00:00Z",
      "Location": "Dr YS Rajasekhara Reddy ACA-VDCA Cricket Stadium",
      "HomeTeam": "DC",
      "AwayTeam": "SRH",
      "result": "None",
      "status": "incomplete",
      "homeTeamRuns": 0,
      "homeTeamWickets": 0,
      "homeTeamOvers": 0,
      "awayTeamRuns": 0,
      "awayTeamWickets": 0,
      "awayTeamOvers": 0
    },
    {
      "MatchNumber": 11,
      "DateUtc": "2025-03-30 14:00:00Z",
      "Location": "ACA Stadium",
      "HomeTeam": "RR",
      "AwayTeam": "CSK",
      "result": "None",
      "status": "incomplete",
      "homeTeamRuns": 0,
      "homeTeamWickets": 0,
      "homeTeamOvers": 0,
      "awayTeamRuns": 0,
      "awayTeamWickets": 0,
      "awayTeamOvers": 0
    },
    {
      "MatchNumber": 12,
      "DateUtc": "2025-03-31 14:00:00Z",
      "Location": "Wankhede Stadium",
      "HomeTeam": "MI",
      "AwayTeam": "KKR",
      "result": "None",
      "status": "incomplete",
      "homeTeamRuns": 0,
      "homeTeamWickets": 0,
      "homeTeamOvers": 0,
      "awayTeamRuns": 0,
      "awayTeamWickets": 0,
      "awayTeamOvers": 0
    },
    {
      "MatchNumber": 13,
      "DateUtc": "2025-04-01 14:00:00Z",
      "Location": "Bharat Ratna Shri Atal Bihari Vajpayee Ekana Cricket Stadium",
      "HomeTeam": "LSG",
      "AwayTeam": "PBKS",
      "result": "None",
      "status": "incomplete",
      "homeTeamRuns": 0,
      "homeTeamWickets": 0,
      "homeTeamOvers": 0,
      "awayTeamRuns": 0,
      "awayTeamWickets": 0,
      "awayTeamOvers": 0
    },
    {
      "MatchNumber": 14,
      "DateUtc": "2025-04-02 14:00:00Z",
      "Location": "M Chinnaswamy Stadium",
      "HomeTeam": "RCB",
      "AwayTeam": "GT",
      "result": "None",
      "status": "incomplete",
      "homeTeamRuns": 0,
      "homeTeamWickets": 0,
      "homeTeamOvers": 0,
      "awayTeamRuns": 0,
      "awayTeamWickets": 0,
      "awayTeamOvers": 0
    },
    {
      "MatchNumber": 15,
      "DateUtc": "2025-04-03 14:00:00Z",
      "Location": "Eden Gardens",
      "HomeTeam": "KKR",
      "AwayTeam": "SRH",
      "result": "None",
      "status": "incomplete",
      "homeTeamRuns": 0,
      "homeTeamWickets": 0,
      "homeTeamOvers": 0,
      "awayTeamRuns": 0,
      "awayTeamWickets": 0,
      "awayTeamOvers": 0
    },
    {
      "MatchNumber": 16,
      "DateUtc": "2025-04-04 14:00:00Z",
      "Location": "Bharat Ratna Shri Atal Bihari Vajpayee Ekana Cricket Stadium",
      "HomeTeam": "LSG",
      "AwayTeam": "MI",
      "result": "None",
      "status": "incomplete",
      "homeTeamRuns": 0,
      "homeTeamWickets": 0,
      "homeTeamOvers": 0,
      "awayTeamRuns": 0,
      "awayTeamWickets": 0,
      "awayTeamOvers": 0
    },
    {
      "MatchNumber": 17,
      "DateUtc": "2025-04-05 10:00:00Z",
      "Location": "MA Chidambaram Stadium",
      "HomeTeam": "CSK",
      "AwayTeam": "DC",
      "result": "None",
      "status": "incomplete",
      "homeTeamRuns": 0,
      "homeTeamWickets": 0,
      "homeTeamOvers": 0,
      "awayTeamRuns": 0,
      "awayTeamWickets": 0,
      "awayTeamOvers": 0
    },
    {
      "MatchNumber": 18,
      "DateUtc": "2025-04-05 14:00:00Z",
      "Location": "New PCA Stadium",
      "HomeTeam": "PBKS",
      "AwayTeam": "RR",
      "result": "None",
      "status": "incomplete",
      "homeTeamRuns": 0,
      "homeTeamWickets": 0,
      "homeTeamOvers": 0,
      "awayTeamRuns": 0,
      "awayTeamWickets": 0,
      "awayTeamOvers": 0
    },
    {
      "MatchNumber": 19,
      "DateUtc": "2025-04-06 10:00:00Z",
      "Location": "Eden Gardens",
      "HomeTeam": "KKR",
      "AwayTeam": "LSG",
      "result": "None",
      "status": "incomplete",
      "homeTeamRuns": 0,
      "homeTeamWickets": 0,
      "homeTeamOvers": 0,
      "awayTeamRuns": 0,
      "awayTeamWickets": 0,
      "awayTeamOvers": 0
    },
    {
      "MatchNumber": 20,
      "DateUtc": "2025-04-06 14:00:00Z",
      "Location": "Rajiv Gandhi International Stadium",
      "HomeTeam": "SRH",
      "AwayTeam": "GT",
      "result": "None",
      "status": "incomplete",
      "homeTeamRuns": 0,
      "homeTeamWickets": 0,
      "homeTeamOvers": 0,
      "awayTeamRuns": 0,
      "awayTeamWickets": 0,
      "awayTeamOvers": 0
    },
    {
      "MatchNumber": 21,
      "DateUtc": "2025-04-07 14:00:00Z",
      "Location": "Wankhede Stadium",
      "HomeTeam": "MI",
      "AwayTeam": "RCB",
      "result": "None",
      "status": "incomplete",
      "homeTeamRuns": 0,
      "homeTeamWickets": 0,
      "homeTeamOvers": 0,
      "awayTeamRuns": 0,
      "awayTeamWickets": 0,
      "awayTeamOvers": 0
    },
    {
      "MatchNumber": 22,
      "DateUtc": "2025-04-08 14:00:00Z",
      "Location": "New PCA Stadium",
      "HomeTeam": "PBKS",
      "AwayTeam": "CSK",
      "result": "None",
      "status": "incomplete",
      "homeTeamRuns": 0,
      "homeTeamWickets": 0,
      "homeTeamOvers": 0,
      "awayTeamRuns": 0,
      "awayTeamWickets": 0,
      "awayTeamOvers": 0
    },
    {
      "MatchNumber": 23,
      "DateUtc": "2025-04-09 14:00:00Z",
      "Location": "Narendra Modi Stadium",
      "HomeTeam": "GT",
      "AwayTeam": "RR",
      "result": "None",
      "status": "incomplete",
      "homeTeamRuns": 0,
      "homeTeamWickets": 0,
      "homeTeamOvers": 0,
      "awayTeamRuns": 0,
      "awayTeamWickets": 0,
      "awayTeamOvers": 0
    },
    {
      "MatchNumber": 24,
      "DateUtc": "2025-04-10 14:00:00Z",
      "Location": "M Chinnaswamy Stadium",
      "HomeTeam": "RCB",
      "AwayTeam": "DC",
      "result": "None",
      "status": "incomplete",
      "homeTeamRuns": 0,
      "homeTeamWickets": 0,
      "homeTeamOvers": 0,
      "awayTeamRuns": 0,
      "awayTeamWickets": 0,
      "awayTeamOvers": 0
    },
    {
      "MatchNumber": 25,
      "DateUtc": "2025-04-11 14:00:00Z",
      "Location": "MA Chidambaram Stadium",
      "HomeTeam": "CSK",
      "AwayTeam": "KKR",
      "result": "None",
      "status": "incomplete",
      "homeTeamRuns": 0,
      "homeTeamWickets": 0,
      "homeTeamOvers": 0,
      "awayTeamRuns": 0,
      "awayTeamWickets": 0,
      "awayTeamOvers": 0
    },
    {
      "MatchNumber": 26,
      "DateUtc": "2025-04-12 10:00:00Z",
      "Location": "Bharat Ratna Shri Atal Bihari Vajpayee Ekana Cricket Stadium",
      "HomeTeam": "LSG",
      "AwayTeam": "GT",
      "result": "None",
      "status": "incomplete",
      "homeTeamRuns": 0,
      "homeTeamWickets": 0,
      "homeTeamOvers": 0,
      "awayTeamRuns": 0,
      "awayTeamWickets": 0,
      "awayTeamOvers": 0
    },
    {
      "MatchNumber": 27,
      "DateUtc": "2025-04-12 14:00:00Z",
      "Location": "Rajiv Gandhi International Stadium",
      "HomeTeam": "SRH",
      "AwayTeam": "PBKS",
      "result": "None",
      "status": "incomplete",
      "homeTeamRuns": 0,
      "homeTeamWickets": 0,
      "homeTeamOvers": 0,
      "awayTeamRuns": 0,
      "awayTeamWickets": 0,
      "awayTeamOvers": 0
    },
    {
      "MatchNumber": 28,
      "DateUtc": "2025-04-13 10:00:00Z",
      "Location": "Sawai Mansingh Stadium",
      "HomeTeam": "RR",
      "AwayTeam": "RCB",
      "result": "None",
      "status": "incomplete",
      "homeTeamRuns": 0,
      "homeTeamWickets": 0,
      "homeTeamOvers": 0,
      "awayTeamRuns": 0,
      "awayTeamWickets": 0,
      "awayTeamOvers": 0
    },
    {
      "MatchNumber": 29,
      "DateUtc": "2025-04-13 14:00:00Z",
      "Location": "Arun Jaitley Stadium",
      "HomeTeam": "DC",
      "AwayTeam": "MI",
      "result": "None",
      "status": "incomplete",
      "homeTeamRuns": 0,
      "homeTeamWickets": 0,
      "homeTeamOvers": 0,
      "awayTeamRuns": 0,
      "awayTeamWickets": 0,
      "awayTeamOvers": 0
    },
    {
      "MatchNumber": 30,
      "DateUtc": "2025-04-14 14:00:00Z",
      "Location": "Bharat Ratna Shri Atal Bihari Vajpayee Ekana Cricket Stadium",
      "HomeTeam": "LSG",
      "AwayTeam": "CSK",
      "result": "None",
      "status": "incomplete",
      "homeTeamRuns": 0,
      "homeTeamWickets": 0,
      "homeTeamOvers": 0,
      "awayTeamRuns": 0,
      "awayTeamWickets": 0,
      "awayTeamOvers": 0
    },
    {
      "MatchNumber": 31,
      "DateUtc": "2025-04-15 14:00:00Z",
      "Location": "New PCA Stadium",
      "HomeTeam": "PBKS",
      "AwayTeam": "KKR",
      "result": "None",
      "status": "incomplete",
      "homeTeamRuns": 0,
      "homeTeamWickets": 0,
      "homeTeamOvers": 0,
      "awayTeamRuns": 0,
      "awayTeamWickets": 0,
      "awayTeamOvers": 0
    },
    {
      "MatchNumber": 32,
      "DateUtc": "2025-04-16 14:00:00Z",
      "Location": "Arun Jaitley Stadium",
      "HomeTeam": "DC",
      "AwayTeam": "RR",
      "result": "None",
      "status": "incomplete",
      "homeTeamRuns": 0,
      "homeTeamWickets": 0,
      "homeTeamOvers": 0,
      "awayTeamRuns": 0,
      "awayTeamWickets": 0,
      "awayTeamOvers": 0
    },
    {
      "MatchNumber": 33,
      "DateUtc": "2025-04-17 14:00:00Z",
      "Location": "Wankhede Stadium",
      "HomeTeam": "MI",
      "AwayTeam": "SRH",
      "result": "None",
      "status": "incomplete",
      "homeTeamRuns": 0,
      "homeTeamWickets": 0,
      "homeTeamOvers": 0,
      "awayTeamRuns": 0,
      "awayTeamWickets": 0,
      "awayTeamOvers": 0
    },
    {
      "MatchNumber": 34,
      "DateUtc": "2025-04-18 14:00:00Z",
      "Location": "M Chinnaswamy Stadium",
      "HomeTeam": "RCB",
      "AwayTeam": "PBKS",
      "result": "None",
      "status": "incomplete",
      "homeTeamRuns": 0,
      "homeTeamWickets": 0,
      "homeTeamOvers": 0,
      "awayTeamRuns": 0,
      "awayTeamWickets": 0,
      "awayTeamOvers": 0
    },
    {
      "MatchNumber": 35,
      "DateUtc": "2025-04-19 10:00:00Z",
      "Location": "Narendra Modi Stadium",
      "HomeTeam": "GT",
      "AwayTeam": "DC",
      "result": "None",
      "status": "incomplete",
      "homeTeamRuns": 0,
      "homeTeamWickets": 0,
      "homeTeamOvers": 0,
      "awayTeamRuns": 0,
      "awayTeamWickets": 0,
      "awayTeamOvers": 0
    },
    {
      "MatchNumber": 36,
      "DateUtc": "2025-04-19 14:00:00Z",
      "Location": "Sawai Mansingh Stadium",
      "HomeTeam": "RR",
      "AwayTeam": "LSG",
      "result": "None",
      "status": "incomplete",
      "homeTeamRuns": 0,
      "homeTeamWickets": 0,
      "homeTeamOvers": 0,
      "awayTeamRuns": 0,
      "awayTeamWickets": 0,
      "awayTeamOvers": 0
    },
    {
      "MatchNumber": 37,
      "DateUtc": "2025-04-20 10:00:00Z",
      "Location": "New PCA Stadium",
      "HomeTeam": "PBKS",
      "AwayTeam": "RCB",
      "result": "None",
      "status": "incomplete",
      "homeTeamRuns": 0,
      "homeTeamWickets": 0,
      "homeTeamOvers": 0,
      "awayTeamRuns": 0,
      "awayTeamWickets": 0,
      "awayTeamOvers": 0
    },
    {
      "MatchNumber": 38,
      "DateUtc": "2025-04-20 14:00:00Z",
      "Location": "Wankhede Stadium",
      "HomeTeam": "MI",
      "AwayTeam": "CSK",
      "result": "None",
      "status": "incomplete",
      "homeTeamRuns": 0,
      "homeTeamWickets": 0,
      "homeTeamOvers": 0,
      "awayTeamRuns": 0,
      "awayTeamWickets": 0,
      "awayTeamOvers": 0
    },
    {
      "MatchNumber": 39,
      "DateUtc": "2025-04-21 14:00:00Z",
      "Location": "Eden Gardens",
      "HomeTeam": "KKR",
      "AwayTeam": "GT",
      "result": "None",
      "status": "incomplete",
      "homeTeamRuns": 0,
      "homeTeamWickets": 0,
      "homeTeamOvers": 0,
      "awayTeamRuns": 0,
      "awayTeamWickets": 0,
      "awayTeamOvers": 0
    },
    {
      "MatchNumber": 40,
      "DateUtc": "2025-04-22 14:00:00Z",
      "Location": "Bharat Ratna Shri Atal Bihari Vajpayee Ekana Cricket Stadium",
      "HomeTeam": "LSG",
      "AwayTeam": "DC",
      "result": "None",
      "status": "incomplete",
      "homeTeamRuns": 0,
      "homeTeamWickets": 0,
      "homeTeamOvers": 0,
      "awayTeamRuns": 0,
      "awayTeamWickets": 0,
      "awayTeamOvers": 0
    },
    {
      "MatchNumber": 41,
      "DateUtc": "2025-04-23 14:00:00Z",
      "Location": "Rajiv Gandhi International Stadium",
      "HomeTeam": "SRH",
      "AwayTeam": "MI",
      "result": "None",
      "status": "incomplete",
      "homeTeamRuns": 0,
      "homeTeamWickets": 0,
      "homeTeamOvers": 0,
      "awayTeamRuns": 0,
      "awayTeamWickets": 0,
      "awayTeamOvers": 0
    },
    {
      "MatchNumber": 42,
      "DateUtc": "2025-04-24 14:00:00Z",
      "Location": "M Chinnaswamy Stadium",
      "HomeTeam": "RCB",
      "AwayTeam": "RR",
      "result": "None",
      "status": "incomplete",
      "homeTeamRuns": 0,
      "homeTeamWickets": 0,
      "homeTeamOvers": 0,
      "awayTeamRuns": 0,
      "awayTeamWickets": 0,
      "awayTeamOvers": 0
    },
    {
      "MatchNumber": 43,
      "DateUtc": "2025-04-25 14:00:00Z",
      "Location": "MA Chidambaram Stadium",
      "HomeTeam": "CSK",
      "AwayTeam": "SRH",
      "result": "None",
      "status": "incomplete",
      "homeTeamRuns": 0,
      "homeTeamWickets": 0,
      "homeTeamOvers": 0,
      "awayTeamRuns": 0,
      "awayTeamWickets": 0,
      "awayTeamOvers": 0
    },
    {
      "MatchNumber": 44,
      "DateUtc": "2025-04-26 14:00:00Z",
      "Location": "Eden Gardens",
      "HomeTeam": "KKR",
      "AwayTeam": "PBKS",
      "result": "None",
      "status": "incomplete",
      "homeTeamRuns": 0,
      "homeTeamWickets": 0,
      "homeTeamOvers": 0,
      "awayTeamRuns": 0,
      "awayTeamWickets": 0,
      "awayTeamOvers": 0
    },
    {
      "MatchNumber": 45,
      "DateUtc": "2025-04-27 10:00:00Z",
      "Location": "Wankhede Stadium",
      "HomeTeam": "MI",
      "AwayTeam": "LSG",
      "result": "None",
      "status": "incomplete",
      "homeTeamRuns": 0,
      "homeTeamWickets": 0,
      "homeTeamOvers": 0,
      "awayTeamRuns": 0,
      "awayTeamWickets": 0,
      "awayTeamOvers": 0
    },
    {
      "MatchNumber": 46,
      "DateUtc": "2025-04-27 14:00:00Z",
      "Location": "Arun Jaitley Stadium",
      "HomeTeam": "DC",
      "AwayTeam": "RCB",
      "result": "None",
      "status": "incomplete",
      "homeTeamRuns": 0,
      "homeTeamWickets": 0,
      "homeTeamOvers": 0,
      "awayTeamRuns": 0,
      "awayTeamWickets": 0,
      "awayTeamOvers": 0
    },
    {
      "MatchNumber": 47,
      "DateUtc": "2025-04-28 14:00:00Z",
      "Location": "Sawai Mansingh Stadium",
      "HomeTeam": "RR",
      "AwayTeam": "GT",
      "result": "None",
      "status": "incomplete",
      "homeTeamRuns": 0,
      "homeTeamWickets": 0,
      "homeTeamOvers": 0,
      "awayTeamRuns": 0,
      "awayTeamWickets": 0,
      "awayTeamOvers": 0
    },
    {
      "MatchNumber": 48,
      "DateUtc": "2025-04-29 14:00:00Z",
      "Location": "Arun Jaitley Stadium",
      "HomeTeam": "DC",
      "AwayTeam": "KKR",
      "result": "None",
      "status": "incomplete",
      "homeTeamRuns": 0,
      "homeTeamWickets": 0,
      "homeTeamOvers": 0,
      "awayTeamRuns": 0,
      "awayTeamWickets": 0,
      "awayTeamOvers": 0
    },
    {
      "MatchNumber": 49,
      "DateUtc": "2025-04-30 14:00:00Z",
      "Location": "MA Chidambaram Stadium",
      "HomeTeam": "CSK",
      "AwayTeam": "PBKS",
      "result": "None",
      "status": "incomplete",
      "homeTeamRuns": 0,
      "homeTeamWickets": 0,
      "homeTeamOvers": 0,
      "awayTeamRuns": 0,
      "awayTeamWickets": 0,
      "awayTeamOvers": 0
    },
    {
      "MatchNumber": 50,
      "DateUtc": "2025-05-01 14:00:00Z",
      "Location": "Sawai Mansingh Stadium",
      "HomeTeam": "RR",
      "AwayTeam": "MI",
      "result": "None",
      "status": "incomplete",
      "homeTeamRuns": 0,
      "homeTeamWickets": 0,
      "homeTeamOvers": 0,
      "awayTeamRuns": 0,
      "awayTeamWickets": 0,
      "awayTeamOvers": 0
    },
    {
      "MatchNumber": 51,
      "DateUtc": "2025-05-02 14:00:00Z",
      "Location": "Narendra Modi Stadium",
      "HomeTeam": "GT",
      "AwayTeam": "SRH",
      "result": "None",
      "status": "incomplete",
      "homeTeamRuns": 0,
      "homeTeamWickets": 0,
      "homeTeamOvers": 0,
      "awayTeamRuns": 0,
      "awayTeamWickets": 0,
      "awayTeamOvers": 0
    },
    {
      "MatchNumber": 52,
      "DateUtc": "2025-05-03 14:00:00Z",
      "Location": "M Chinnaswamy Stadium",
      "HomeTeam": "RCB",
      "AwayTeam": "CSK",
      "result": "None",
      "status": "incomplete",
      "homeTeamRuns": 0,
      "homeTeamWickets": 0,
      "homeTeamOvers": 0,
      "awayTeamRuns": 0,
      "awayTeamWickets": 0,
      "awayTeamOvers": 0
    },
    {
      "MatchNumber": 53,
      "DateUtc": "2025-05-04 10:00:00Z",
      "Location": "Eden Gardens",
      "HomeTeam": "KKR",
      "AwayTeam": "RR",
      "result": "None",
      "status": "incomplete",
      "homeTeamRuns": 0,
      "homeTeamWickets": 0,
      "homeTeamOvers": 0,
      "awayTeamRuns": 0,
      "awayTeamWickets": 0,
      "awayTeamOvers": 0
    },
    {
      "MatchNumber": 54,
      "DateUtc": "2025-05-04 14:00:00Z",
      "Location": "Himachal Pradesh Cricket Association Stadium",
      "HomeTeam": "PBKS",
      "AwayTeam": "LSG",
      "result": "None",
      "status": "incomplete",
      "homeTeamRuns": 0,
      "homeTeamWickets": 0,
      "homeTeamOvers": 0,
      "awayTeamRuns": 0,
      "awayTeamWickets": 0,
      "awayTeamOvers": 0
    },
    {
      "MatchNumber": 55,
      "DateUtc": "2025-05-05 14:00:00Z",
      "Location": "Rajiv Gandhi International Stadium",
      "HomeTeam": "SRH",
      "AwayTeam": "DC",
      "result": "None",
      "status": "incomplete",
      "homeTeamRuns": 0,
      "homeTeamWickets": 0,
      "homeTeamOvers": 0,
      "awayTeamRuns": 0,
      "awayTeamWickets": 0,
      "awayTeamOvers": 0
    },
    {
      "MatchNumber": 56,
      "DateUtc": "2025-05-06 14:00:00Z",
      "Location": "Wankhede Stadium",
      "HomeTeam": "MI",
      "AwayTeam": "GT",
      "result": "None",
      "status": "incomplete",
      "homeTeamRuns": 0,
      "homeTeamWickets": 0,
      "homeTeamOvers": 0,
      "awayTeamRuns": 0,
      "awayTeamWickets": 0,
      "awayTeamOvers": 0
    },
    {
      "MatchNumber": 57,
      "DateUtc": "2025-05-07 14:00:00Z",
      "Location": "Eden Gardens",
      "HomeTeam": "KKR",
      "AwayTeam": "CSK",
      "result": "None",
      "status": "incomplete",
      "homeTeamRuns": 0,
      "homeTeamWickets": 0,
      "homeTeamOvers": 0,
      "awayTeamRuns": 0,
      "awayTeamWickets": 0,
      "awayTeamOvers": 0
    },
    {
      "MatchNumber": 58,
      "DateUtc": "2025-05-17 14:00:00Z",
      "Location": "M Chinnaswamy Stadium",
      "HomeTeam": "RCB",
      "AwayTeam": "KKR",
      "result": "None",
      "status": "incomplete",
      "homeTeamRuns": 0,
      "homeTeamWickets": 0,
      "homeTeamOvers": 0,
      "awayTeamRuns": 0,
      "awayTeamWickets": 0,
      "awayTeamOvers": 0
    },
    {
      "MatchNumber": 59,
      "DateUtc": "2025-05-18 10:00:00Z",
      "Location": "Sawai Mansingh Stadium",
      "HomeTeam": "RR",
      "AwayTeam": "PBKS",
      "result": "None",
      "status": "incomplete",
      "homeTeamRuns": 0,
      "homeTeamWickets": 0,
      "homeTeamOvers": 0,
      "awayTeamRuns": 0,
      "awayTeamWickets": 0,
      "awayTeamOvers": 0
    },
    {
      "MatchNumber": 60,
      "DateUtc": "2025-05-18 14:00:00Z",
      "Location": "Arun Jaitley Stadium",
      "HomeTeam": "DC",
      "AwayTeam": "GT",
      "result": "None",
      "status": "incomplete",
      "homeTeamRuns": 0,
      "homeTeamWickets": 0,
      "homeTeamOvers": 0,
      "awayTeamRuns": 0,
      "awayTeamWickets": 0,
      "awayTeamOvers": 0
    },
    {
      "MatchNumber": 61,
      "DateUtc": "2025-05-19 14:00:00Z",
      "Location": "Bharat Ratna Shri Atal Bihari Vajpayee Ekana Cricket Stadium",
      "HomeTeam": "LSG",
      "AwayTeam": "SRH",
      "result": "None",
      "status": "incomplete",
      "homeTeamRuns": 0,
      "homeTeamWickets": 0,
      "homeTeamOvers": 0,
      "awayTeamRuns": 0,
      "awayTeamWickets": 0,
      "awayTeamOvers": 0
    },
    {
      "MatchNumber": 62,
      "DateUtc": "2025-05-20 14:00:00Z",
      "Location": "Arun Jaitley Stadium",
      "HomeTeam": "CSK",
      "AwayTeam": "RR",
      "result": "None",
      "status": "incomplete",
      "homeTeamRuns": 0,
      "homeTeamWickets": 0,
      "homeTeamOvers": 0,
      "awayTeamRuns": 0,
      "awayTeamWickets": 0,
      "awayTeamOvers": 0
    },
    {
      "MatchNumber": 63,
      "DateUtc": "2025-05-21 14:00:00Z",
      "Location": "Wankhede Stadium",
      "HomeTeam": "MI",
      "AwayTeam": "DC",
      "result": "None",
      "status": "incomplete",
      "homeTeamRuns": 0,
      "homeTeamWickets": 0,
      "homeTeamOvers": 0,
      "awayTeamRuns": 0,
      "awayTeamWickets": 0,
      "awayTeamOvers": 0
    },
    {
      "MatchNumber": 64,
      "DateUtc": "2025-05-22 14:00:00Z",
      "Location": "Narendra Modi Stadium",
      "HomeTeam": "GT",
      "AwayTeam": "LSG",
      "result": "None",
      "status": "incomplete",
      "homeTeamRuns": 0,
      "homeTeamWickets": 0,
      "homeTeamOvers": 0,
      "awayTeamRuns": 0,
      "awayTeamWickets": 0,
      "awayTeamOvers": 0
    },
    {
      "MatchNumber": 65,
      "DateUtc": "2025-05-23 14:00:00Z",
      "Location": "M Chinnaswamy Stadium",
      "HomeTeam": "RCB",
      "AwayTeam": "SRH",
      "result": "None",
      "status": "incomplete",
      "homeTeamRuns": 0,
      "homeTeamWickets": 0,
      "homeTeamOvers": 0,
      "awayTeamRuns": 0,
      "awayTeamWickets": 0,
      "awayTeamOvers": 0
    },
    {
      "MatchNumber": 66,
      "DateUtc": "2025-05-24 14:00:00Z",
      "Location": "Sawai Mansingh Stadium",
      "HomeTeam": "PBKS",
      "AwayTeam": "DC",
      "result": "None",
      "status": "incomplete",
      "homeTeamRuns": 0,
      "homeTeamWickets": 0,
      "homeTeamOvers": 0,
      "awayTeamRuns": 0,
      "awayTeamWickets": 0,
      "awayTeamOvers": 0
    },
    {
      "MatchNumber": 67,
      "DateUtc": "2025-05-25 10:00:00Z",
      "Location": "Narendra Modi Stadium",
      "HomeTeam": "GT",
      "AwayTeam": "CSK",
      "result": "None",
      "status": "incomplete",
      "homeTeamRuns": 0,
      "homeTeamWickets": 0,
      "homeTeamOvers": 0,
      "awayTeamRuns": 0,
      "awayTeamWickets": 0,
      "awayTeamOvers": 0
    },
    {
      "MatchNumber": 68,
      "DateUtc": "2025-05-25 14:00:00Z",
      "Location": "Arun Jaitley Stadium",
      "HomeTeam": "SRH",
      "AwayTeam": "KKR",
      "result": "None",
      "status": "incomplete",
      "homeTeamRuns": 0,
      "homeTeamWickets": 0,
      "homeTeamOvers": 0,
      "awayTeamRuns": 0,
      "awayTeamWickets": 0,
      "awayTeamOvers": 0
    },
    {
      "MatchNumber": 69,
      "DateUtc": "2025-05-26 14:00:00Z",
      "Location": "Sawai Mansingh Stadium",
      "HomeTeam": "PBKS",
      "AwayTeam": "MI",
      "result": "None",
      "status": "incomplete",
      "homeTeamRuns": 0,
      "homeTeamWickets": 0,
      "homeTeamOvers": 0,
      "awayTeamRuns": 0,
      "awayTeamWickets": 0,
      "awayTeamOvers": 0
    },
    {
      "MatchNumber": 70,
      "DateUtc": "2025-05-27 14:00:00Z",
      "Location": "Bharat Ratna Shri Atal Bihari Vajpayee Ekana Cricket Stadium",
      "HomeTeam": "LSG",
      "AwayTeam": "RCB",
      "result": "None",
      "status": "incomplete",
      "homeTeamRuns": 0,
      "homeTeamWickets": 0,
      "homeTeamOvers": 0,
      "awayTeamRuns": 0,
      "awayTeamWickets": 0,
      "awayTeamOvers": 0
    }
  ]
}